setup.cfg
setup.py
pcommerce/__init__.py
pcommerce.payment.docdata.egg-info/PKG-INFO
pcommerce.payment.docdata.egg-info/SOURCES.txt
pcommerce.payment.docdata.egg-info/dependency_links.txt
pcommerce.payment.docdata.egg-info/entry_points.txt
pcommerce.payment.docdata.egg-info/namespace_packages.txt
pcommerce.payment.docdata.egg-info/not-zip-safe
pcommerce.payment.docdata.egg-info/requires.txt
pcommerce.payment.docdata.egg-info/top_level.txt
pcommerce/payment/__init__.py
pcommerce/payment/docdata/__init__.py
pcommerce/payment/docdata/controlpanel.py
pcommerce/payment/docdata/data.py
pcommerce/payment/docdata/interfaces.py
pcommerce/payment/docdata/plugin.py
pcommerce/payment/docdata/browser/__init__.py
pcommerce/payment/docdata/browser/confirmation.py
pcommerce/payment/docdata/browser/overview.py
pcommerce/payment/docdata/browser/payment.py
pcommerce/payment/docdata/browser/process.py
pcommerce/payment/docdata/docdata/__init__.py
pcommerce/payment/docdata/docdata/exceptions.py
pcommerce/payment/docdata/docdata/interface.py