Metadata-Version: 1.1
Name: pcommerce.payment.docdata
Version: 1.1
Summary: Docdata payment plugin for PCommerce
Home-page: http://www.gw20e.com
Author: Huub Bouma
Author-email: support@gw20e.com
License: GPL
Platform: UNKNOWN
Classifier: Programming Language :: Python
Classifier: Topic :: Software Development :: Libraries :: Python Modules
